pystf3d/__init__.py
pystf3d/config.py
pystf3d/datacontainer.py
pystf3d/geo_util.py
pystf3d/io.py
pystf3d/measure.py
pystf3d/plot.py
pystf3d/signal.py
pystf3d/stf3d.py
pystf3d/util.py
tests/__init__.py
tests/test_config.py
tests/test_data_container.py
tests/test_geo_util.py
tests/test_measure.py
tests/test_signal.py
tests/test_util.py
pystf3d-0.0.1.dist-info/METADATA
pystf3d-0.0.1.dist-info/WHEEL
pystf3d-0.0.1.dist-info/top_level.txt
pystf3d-0.0.1.dist-info/RECORD
