Metadata-Version: 2.1
Name: pystf3d
Version: 0.0.1
Summary: Global 3D Source Time Function Inversion Tool
Home-page: https://github.com/lsawade/GCMT3D
Author: Lucas Sawade
Author-email: lsawade@princeton.edu
License: GNU Lesser General Public License, Version 3
Keywords: Global,Source Time Function Inversion,Specfem
Platform: UNKNOWN
Classifier: Development Status :: 4 - Beta
Classifier: Topic :: Utilities
Classifier: License :: OSI Approved :: GNU General Public License v3 or later (GPLv3+)
Provides-Extra: docs
Requires-Dist: sphinx ; extra == 'docs'
Requires-Dist: sphinx-rtd-theme ; extra == 'docs'
Provides-Extra: tests
Requires-Dist: pytest ; extra == 'tests'
Requires-Dist: py ; extra == 'tests'
